security_headers/__init__.py
security_headers/admin.py
security_headers/apps.py
security_headers/defaults.py
security_headers/middleware.py
security_headers/models.py
security_headers/settings.py
security_headers/urls.py
security_headers/views.py
security_headers/migrations/0001_initial.py
security_headers/migrations/__init__.py
security_headers/templates/security_headers/heartbeat.html
security_headers/templates/security_headers/scan.html
django_security_headers-0.2.5.dist-info/LICENSE
django_security_headers-0.2.5.dist-info/METADATA
django_security_headers-0.2.5.dist-info/WHEEL
django_security_headers-0.2.5.dist-info/top_level.txt
django_security_headers-0.2.5.dist-info/RECORD
